<?xml version="1.0" encoding="utf-8" ?>
<dwsync>
<file name="index.php" server="tecreytics.com" local="132499739928229723" remote="132499956000000000" Dst="1" />
<file name="home.php" server="tecreytics.com" local="132501061622050415" remote="132501277800000000" Dst="1" />
<file name="alumnos.php" server="tecreytics.com" local="132501404277123706" remote="132501619800000000" Dst="1" />
<file name="alumnosReg.php" server="tecreytics.com" local="132501096295870584" remote="132501619800000000" Dst="1" />
<file name="alumnosEdit.php" server="tecreytics.com" local="132501404353260735" remote="132501619800000000" Dst="1" />
<file name="alumnosBorrar.php" server="tecreytics.com" local="132501223984082999" remote="132501439800000000" Dst="1" />
<file name="maestros.php" server="tecreytics.com" local="132501416932149118" remote="132501632400000000" Dst="1" />
<file name="maestrosReg.php" server="tecreytics.com" local="132501421086998229" remote="132501636600000000" Dst="1" />
</dwsync>